mcp_youtube_extract/__init__.py
mcp_youtube_extract/logger.py
mcp_youtube_extract/server.py
mcp_youtube_extract/youtube.py
mcp_youtube_extract-0.1.0.dist-info/METADATA
mcp_youtube_extract-0.1.0.dist-info/WHEEL
mcp_youtube_extract-0.1.0.dist-info/entry_points.txt
mcp_youtube_extract-0.1.0.dist-info/licenses/LICENSE
mcp_youtube_extract-0.1.0.dist-info/RECORD
