Metadata-Version: 2.4
Name: mcp_youtube_extract
Version: 0.1.0
Summary: A Model Context Protocol (MCP) server for YouTube operations
License-File: LICENSE
Requires-Python: >=3.13
Requires-Dist: google-api-python-client>=2.172.0
Requires-Dist: mcp>=1.6.0
Requires-Dist: youtube-transcript-api>=1.1.0
